{"cameraMode":{"drawMode":0,"name":"Shaded","section":"Shading Mode"},"sceneLighting":true,"audioPlay":false,"sceneViewState":{"showFog":true,"showMaterialUpdate":false,"showSkybox":true,"showFlares":true,"showImageEffects":true,"showParticleSystems":true},"in2DMode":false,"pivot":{"x":21.556415557861329,"y":2.8989415168762209,"z":-14.773154258728028},"rotation":{"x":-0.10054297745227814,"y":-0.8606253266334534,"z":0.18802490830421449,"w":-0.4630134701728821},"size":2.236936330795288,"orthographic":false}